transbigdata/__init__.py
transbigdata/activity.py
transbigdata/bikedata.py
transbigdata/busgps.py
transbigdata/coordinates.py
transbigdata/crawler.py
transbigdata/gisprocess.py
transbigdata/grids.py
transbigdata/metro.py
transbigdata/mobilephonedata.py
transbigdata/odprocess.py
transbigdata/plotmap.py
transbigdata/preprocess.py
transbigdata/quality.py
transbigdata/taxigps.py
transbigdata/traj.py
transbigdata/utils.py
transbigdata/visualization.py
transbigdata-0.5.3.dist-info/LICENSE
transbigdata-0.5.3.dist-info/METADATA
transbigdata-0.5.3.dist-info/WHEEL
transbigdata-0.5.3.dist-info/top_level.txt
transbigdata-0.5.3.dist-info/RECORD
