Metadata-Version: 2.1
Name: transbigdata
Version: 0.5.3
Summary: A Python package developed for transportation spatio-temporal big data processing and analysis.
Home-page: https://github.com/ni1o1/transbigdata
Author: Qing Yu
Author-email: qingyu0815@foxmail.com
License: BSD
Project-URL: Bug Tracker, https://github.com/ni1o1/transbigdata/issues
Classifier: Operating System :: OS Independent
Classifier: Topic :: Text Processing :: Indexing
Classifier: Topic :: Utilities
Classifier: Topic :: Software Development :: Libraries :: Python Modules
Classifier: License :: OSI Approved :: BSD License
Classifier: Programming Language :: Python
Classifier: Programming Language :: Python :: 3.7
Classifier: Programming Language :: Python :: 3.8
Classifier: Programming Language :: Python :: 3.9
Requires-Python: >=3.6
License-File: LICENSE
Requires-Dist: numpy
Requires-Dist: pandas
Requires-Dist: shapely
Requires-Dist: geopandas >=0.10.2
Requires-Dist: scipy
Requires-Dist: matplotlib
Requires-Dist: pykalman
Requires-Dist: osmnx
